{
  "id": "infrastructure/statsig_domains",
  "title": "Statsig Domains",
  "description": "Statsig uses the following domain names for its services. If you have a network policy set up inside your systems, you should allowlist",
  "source": "@site/docs/infrastructure/statsig_domains.md",
  "sourceDirName": "infrastructure",
  "slug": "/infrastructure/statsig_domains",
  "permalink": "/infrastructure/statsig_domains",
  "draft": false,
  "unlisted": false,
  "editUrl": "https://github.com/statsig-io/docs/edit/main/docs/infrastructure/statsig_domains.md",
  "tags": [],
  "version": "current",
  "lastUpdatedAt": 1758153600000,
  "frontMatter": {
    "title": "Statsig Domains",
    "keywords": [
      "owner:eric"
    ],
    "last_update": {
      "date": "2025-09-18T00:00:00.000Z"
    }
  },
  "sidebar": "cloud",
  "previous": {
    "title": "Statsig IP Ranges",
    "permalink": "/infrastructure/statsig_ip_ranges"
  },
  "next": {
    "title": "API Proxy",
    "permalink": "/infrastructure/api_proxy/introduction"
  }
}